simdy/__init__.py
simdy/acum.py
simdy/args.py
simdy/arr.py
simdy/asin_acos.py
simdy/asm_gen.py
simdy/atan.py
simdy/built_ins.py
simdy/cgen.py
simdy/conv.py
simdy/cos.py
simdy/cpy.py
simdy/dbl_arg.py
simdy/dbl_vec_arg.py
simdy/exp.py
simdy/expr.py
simdy/flt_arg.py
simdy/flt_vec_arg.py
simdy/gbuilt_ins.py
simdy/holders.py
simdy/int_arg.py
simdy/int_vec_arg.py
simdy/kernel.py
simdy/loc_args.py
simdy/log.py
simdy/mask.py
simdy/opt.py
simdy/parser.py
simdy/pow.py
simdy/pown.py
simdy/ptr.py
simdy/regs.py
simdy/select.py
simdy/sin.py
simdy/stms.py
simdy/strc_arg.py
simdy/tan.py
simdy/test.py
simdy/usr_typ.py
simdy/util.py
simdy-0.6.1.dist-info/DESCRIPTION.rst
simdy-0.6.1.dist-info/METADATA
simdy-0.6.1.dist-info/RECORD
simdy-0.6.1.dist-info/WHEEL
simdy-0.6.1.dist-info/metadata.json
simdy-0.6.1.dist-info/top_level.txt
