Metadata-Version: 2.0
Name: simdy
Version: 0.6.1
Summary: Fast computing using simd instructions.
Home-page: https://bitbucket.org/Tahir007/simdy
Author: Mario Vidov
Author-email: mvidov@yahoo.com
License: MIT
Keywords: simd SSE AVX FMA AVX-512
Platform: UNKNOWN
Classifier: Intended Audience :: Developers
Classifier: Topic :: Software Development :: Code Generators
Classifier: License :: OSI Approved :: MIT License
Classifier: Programming Language :: Python :: 3.5
Classifier: Programming Language :: Python :: 3.6
Requires-Dist: tdasm
